Metadata-Version: 2.1
Name: django-cas-agn
Version: 4.1.2
Summary: Django CAS 1.0/2.0/3.0 client authentication library, support Django 2.0, 2.1, 2.2, 3.0 and Python 3.5+
Home-page: https://djangocas.dev
Author: Ming Chen
Author-email: ming@djangocas.dev
License: BSD
Download-URL: https://github.com/agn-7/django-cas-agn/releases
Keywords: django,cas,cas2,cas3,client,sso,single sign-on,Central Authentication Service,authentication,auth
Platform: UNKNOWN
Classifier: Development Status :: 5 - Production/Stable
Classifier: Environment :: Web Environment
Classifier: Framework :: Django
Classifier: Framework :: Django :: 2.0
Classifier: Framework :: Django :: 2.1
Classifier: Framework :: Django :: 2.2
Classifier: Framework :: Django :: 3.0
Classifier: Intended Audience :: Developers
Classifier: License :: OSI Approved :: MIT License
Classifier: Natural Language :: English
Classifier: Operating System :: OS Independent
Classifier: Programming Language :: Python
Classifier: Programming Language :: Python :: 3
Classifier: Programming Language :: Python :: 3 :: Only
Classifier: Programming Language :: Python :: 3.5
Classifier: Programming Language :: Python :: 3.6
Classifier: Programming Language :: Python :: 3.7
Classifier: Programming Language :: Python :: 3.8
Classifier: Topic :: Internet :: WWW/HTTP
Requires-Python: >=3.5
Requires-Dist: Django (>=2.0)
Requires-Dist: python-cas (>=1.4.0)
